{
"chancellor": "rollecnahc",
"still": "llits",
"length": "htgnel",
"was": "saw",
"little": "elttil",
"just": "tsuj",
"lower": "rewol",
"does": "seod",
"decided": "dediced",
"thus": "suht",
"and": "dna",
"moral": "larom",
"long": "gnol",
"acting": "gnitca",
"at": "ta",
"penetration": "noitartenep",
"father": "rehtaf",
"fact": "tcaf",
"influence": "ecneulfni",
"week": "keew",
"protogeometric": "cirtemoegotorp",
"ripple": "elppir",
"q": "q",
"residential": "laitnediser",
"sitter": "rettis",
"see": "ees",
"young": "gnuoy",
"conservatory": "yrotavresnoc",
"professional": "lanoisseforp",
"did": "did",
"audience": "ecneidua",
"violin": "niloiv",
"some": "emos",
"forward": "drawrof",
"level": "level",
"actor": "rotca",
"argentina": "anitnegra",
"indignation": "noitangidni",
"think": "kniht",
"business": "ssenisub",
"measure": "erusaem",
"smooth": "htooms",
"eighth": "hthgie",
"being": "gnieb",
"racing": "gnicar",
"mile": "elim",
"up": "pu",
"for": "rof",
"grandma": "amdnarg",
"virtue": "eutriv",
"do": "od",
"few": "wef",
"where": "erehw",
"growing": "gniworg",
"into": "otni",
"alan": "nala",
"study": "yduts",
"strenuous": "suounerts",
"loathing": "gnihtaol",
"we": "ew",
"referent": "tnerefer",
"modest": "tsedom",
"such": "hcus",
"drive": "evird",
"molecular": "ralucelom",
"throughout": "tuohguorht",
"plan": "nalp",
"part": "trap",
"negro": "orgen",
"position": "noitisop",
"behavioral": "laroivaheb",
"professor": "rosseforp",
"my": "ym",
"saline": "enilas",
"austin": "nitsua",
"here": "ereh",
"bronchial": "laihcnorb",
"late": "etal",
"northern": "nrehtron",
"new": "wen",
"of": "fo",
"suggest": "tseggus",
"red": "der",
"lamb": "bmal",
"conflict": "tcilfnoc",
"in": "ni",
"out": "tuo",
"foamy": "ymaof",
"clear": "raelc",
"jacket": "tekcaj",
"boat": "taob",
"one": "eno",
"leaving": "gnivael",
"proved": "devorp",
"college": "egelloc",
"king": "gnik",
"protect": "tcetorp",
"slept": "tpels",
"many": "ynam",
"fatima": "amitaf",
"why": "yhw",
"strategy": "ygetarts",
"joy": "yoj",
"taught": "thguat",
"parasympathetic": "citehtapmysarap",
"heading": "gnidaeh",
"alley": "yella",
"association": "noitaicossa",
"lizzie": "eizzil",
"social": "laicos",
"coal": "laoc",
"however": "revewoh",
"expressway": "yawsserpxe",
"right": "thgir",
"now": "won",
"any": "yna",
"presence": "ecneserp",
"even": "neve",
"light": "thgil",
"dweller": "rellewd",
"panic": "cinap",
"reason": "nosaer",
"state": "etats",
"hospital": "latipsoh",
"covering": "gnirevoc",
"ralph": "hplar",
"resident": "tnediser",
"i": "i",
"drew": "werd",
"source": "ecruos",
"influx": "xulfni",
"different": "tnereffid",
"information": "noitamrofni",
"wee": "eew",
"white": "etihw",
"testament": "tnematset",
"get": "teg",
"fixed": "dexif",
"perhaps": "spahrep",
"could": "dluoc",
"field": "dleif",
"bases": "sesab",
"inner": "renni",
"fire": "erif",
"mainly": "ylniam",
"military": "yratilim",
"merger": "regrem",
"kappa": "appak",
"funds": "sdnuf",
"attention": "noitnetta",
"inconceivable": "elbaviecnocni",
"expression": "noisserpxe",
"degree": "eerged",
"like": "ekil",
"man": "nam",
"sensory": "yrosnes",
"no": "on",
"three": "eerht",
"while": "elihw",
"tradition": "noitidart",
"times": "semit",
"marry": "yrram",
"arm": "mra",
"orchestra": "artsehcro",
"higher": "rehgih",
"potential": "laitnetop",
"suddenly": "ylneddus",
"hyperbolic": "cilobrepyh",
"indirect": "tceridni",
"past": "tsap",
"days": "syad",
"commit": "timmoc",
"incorporate": "etaroprocni",
"understood": "dootsrednu",
"officially": "yllaiciffo",
"found": "dnuof",
"sent": "tnes",
"room": "moor",
"they": "yeht",
"max": "xam",
"hans": "snah",
"said": "dias",
"greedy": "ydeerg",
"morning": "gninrom",
"may": "yam",
"river": "revir",
"farm": "mraf",
"ground": "dnuorg",
"sample": "elpmas",
"anyone": "enoyna",
"separate": "etarapes",
"average": "egareva",
"law": "wal",
"felt": "tlef",
"gas": "sag",
"calm": "mlac",
"covered": "derevoc",
"getting": "gnitteg",
"cure": "eruc",
"condition": "noitidnoc",
"virulence": "ecneluriv",
"unemployment": "tnemyolpmenu",
"local": "lacol",
"phosphor": "rohpsohp",
"job": "boj",
"evolution": "noitulove",
"about": "tuoba",
"mean": "naem",
"can": "nac",
"export": "tropxe",
"standard": "dradnats",
"outstanding": "gnidnatstuo",
"service": "ecivres",
"cook": "kooc",
"already": "ydaerla",
"certain": "niatrec",
"thoroughly": "ylhguoroht",
"cabbage": "egabbac",
"money": "yenom",
"between": "neewteb",
"foot": "toof",
"family": "ylimaf",
"spume": "emups",
"oil": "lio",
"be": "eb",
"county": "ytnuoc",
"place": "ecalp",
"unshelled": "dellehsnu",
"hemoglobin": "nibolgomeh",
"peter": "retep",
"break": "kaerb",
"available": "elbaliava",
"negative": "evitagen",
"been": "neeb",
"each": "hcae",
"together": "rehtegot",
"someone": "enoemos",
"to": "ot",
"it": "ti",
"initial": "laitini",
"surprising": "gnisirprus",
"eagerly": "ylregae",
"unknown": "nwonknu",
"underlying": "gniylrednu",
"rising": "gnisir",
"deliberate": "etarebiled",
"reciprocal": "lacorpicer",
"stage": "egats",
"deny": "yned",
"with": "htiw",
"so": "os",
"across": "ssorca",
"park": "krap",
"cent": "tnec",
"twenty": "ytnewt",
"steadily": "ylidaets",
"incident": "tnedicni",
"seem": "mees",
"defense": "esnefed",
"their": "rieht",
"met": "tem",
"nicolas": "salocin",
"antietam": "mateitna",
"editor": "rotide",
"federal": "laredef",
"last": "tsal",
"he": "eh",
"whole": "elohw",
"give": "evig",
"extreme": "emertxe",
"plank": "knalp",
"range": "egnar",
"none": "enon",
"foe": "eof",
"recent": "tnecer",
"the": "eht",
"jutting": "gnittuj",
"much": "hcum",
"were": "erew",
"during": "gnirud",
"that": "taht",
"experience": "ecneirepxe",
"over": "revo",
"vacuolization": "noitaziloucav",
"braced": "decarb",
"kerygma": "amgyrek",
"working": "gnikrow",
"or": "ro",
"oklahoma": "amohalko",
"providence": "ecnedivorp",
"less": "ssel",
"impose": "esopmi",
"gone": "enog",
"shell": "llehs",
"far": "raf",
"assumed": "demussa",
"examine": "enimaxe",
"through": "hguorht",
"fight": "thgif",
"task": "ksat",
"she": "ehs",
"step": "pets",
"a": "a",
"upon": "nopu",
"going": "gniog",
"sought": "thguos",
"senator": "rotanes",
"essentially": "yllaitnesse",
"head": "daeh",
"bobby": "ybbob",
"until": "litnu",
"master": "retsam",
"all": "lla",
"benefactor": "rotcafeneb",
"ask": "ksa",
"given": "nevig",
"respect": "tcepser",
"public": "cilbup",
"tell": "llet",
"gain": "niag",
"preoccupation": "noitapuccoerp",
"from": "morf",
"there": "ereht",
"barely": "ylerab",
"conduct": "tcudnoc",
"involved": "devlovni",
"beautiful": "lufituaeb",
"glow": "wolg",
"weak": "kaew",
"chill": "llihc",
"fighting": "gnithgif",
"per": "rep",
"left": "tfel",
"then": "neht",
"modern": "nredom",
"win": "niw",
"stimulation": "noitalumits",
"tested": "detset",
"precious": "suoicerp",
"find": "dnif",
"advantage": "egatnavda",
"two": "owt",
"green": "neerg",
"crossroads": "sdaorssorc",
"surviving": "gnivivrus",
"excellent": "tnellecxe",
"water": "retaw",
"popularly": "ylralupop",
"choice": "eciohc",
"corporate": "etaroproc",
"day": "yad",
"absence": "ecnesba",
"sandman": "namdnas",
"commission": "noissimmoc",
"needlessly": "ylsseldeen",
"institute": "etutitsni",
"crowd": "dworc",
"which": "hcihw",
"channel": "lennahc",
"work": "krow",
"high": "hgih",
"building": "gnidliub",
"company": "ynapmoc",
"separately": "yletarapes",
"must": "tsum",
"not": "ton",
"freight": "thgierf",
"french": "hcnerf",
"its": "sti",
"organic": "cinagro",
"board": "draob",
"have": "evah",
"again": "niaga",
"butt": "ttub",
"palfrey": "yerflap",
"setback": "kcabtes",
"more": "erom",
"samuel": "leumas",
"case": "esac",
"guard": "draug",
"apparently": "yltnerappa",
"space": "ecaps",
"distribution": "noitubirtsid",
"school": "loohcs",
"year": "raey",
"but": "tub",
"program": "margorp",
"minimum": "muminim",
"bed": "deb",
"war": "raw",
"rotary": "yrator",
"highway": "yawhgih",
"though": "hguoht",
"are": "era",
"march": "hcram",
"culprit": "tirpluc",
"only": "ylno",
"certainly": "ylniatrec",
"poison": "nosiop",
"automobile": "elibomotua",
"unanimously": "ylsuominanu",
"crystal": "latsyrc",
"wall": "llaw",
"gold": "dlog",
"disarray": "yarrasid",
"observer": "revresbo",
"support": "troppus",
"soberly": "ylrebos",
"ambuscade": "edacsubma",
"cunning": "gninnuc",
"old": "dlo",
"close": "esolc",
"once": "ecno",
"say": "yas",
"grammatical": "lacitammarg",
"back": "kcab",
"also": "osla",
"bark": "krab",
"tub": "but",
"violent": "tneloiv",
"forgotten": "nettogrof",
"way": "yaw",
"colors": "sroloc",
"fresh": "hserf",
"jackson": "noskcaj",
"surface": "ecafrus",
"put": "tup",
"got": "tog",
"lightly": "ylthgil",
"unlimited": "detimilnu",
"him": "mih",
"busted": "detsub",
"banal": "lanab",
"lie": "eil",
"appear": "raeppa",
"squad": "dauqs",
"those": "esoht",
"mouth": "htuom",
"permanent": "tnenamrep",
"beneficial": "laicifeneb",
"share": "erahs",
"relativity": "ytivitaler",
"rough": "hguor",
"miracle": "elcarim",
"mark": "kram",
"make": "ekam",
"after": "retfa",
"air": "ria",
"pressure": "erusserp",
"aid": "dia",
"city": "ytic",
"consumption": "noitpmusnoc",
"outside": "edistuo",
"well": "llew",
"ornate": "etanro",
"believe": "eveileb",
"short": "trohs",
"typical": "lacipyt",
"natal": "latan",
"change": "egnahc",
"educational": "lanoitacude",
"her": "reh",
"neck": "kcen",
"gradually": "yllaudarg",
"training": "gniniart",
"den": "ned",
"brains": "sniarb",
"saturday": "yadrutas",
"characteristic": "citsiretcarahc",
"first": "tsrif",
"these": "eseht",
"this": "siht",
"other": "rehto",
"ready": "ydaer",
"his": "sih",
"problem": "melborp",
"heart": "traeh",
"east": "tsae",
"focus": "sucof",
"brilliant": "tnaillirb",
"had": "dah",
"wrong": "gnorw",
"as": "sa",
"identical": "lacitnedi",
"floor": "roolf",
"go": "og",
"yes": "sey",
"drove": "evord",
"hat": "tah",
"by": "yb",
"smile": "elims",
"thought": "thguoht",
"love": "evol",
"issue": "eussi",
"trip": "pirt",
"swung": "gnuws",
"vocational": "lanoitacov",
"forth": "htrof",
"twelve": "evlewt",
"is": "si",
"because": "esuaceb",
"tall": "llat",
"communism": "msinummoc",
"shed": "dehs",
"understandable": "elbadnatsrednu",
"bay": "yab",
"sacrifice": "ecifircas",
"class": "ssalc",
"welfare": "eraflew",
"final": "lanif",
"despite": "etipsed",
"essential": "laitnesse",
"spread": "daerps",
"art": "tra",
"when": "nehw",
"an": "na",
"retorted": "detroter",
"fail": "liaf",
"another": "rehtona",
"missing": "gnissim",
"you": "uoy",
"if": "fi",
"nature": "erutan",
"foolish": "hsiloof",
"on": "no",
"steady": "ydaets",
"obtainable": "elbaniatbo",
"will": "lliw",
"before": "erofeb",
"sure": "erus",
"who": "ohw",
"them": "meht"
}
